[
  {
    "isim": "Inception",
    "tür": "Bilim Kurgu",
    "çıkışYılı": 2010,
    "kapakURL": "https://example.com/kapak/inception.jpg",
    "bannerURL": "https://example.com/banner/inception.jpg",
    "açıklama": "Rüyaların içinde yolculuk yapan bir hırsızın hikayesi.",
    "puan": 8.8,
    "dil": "İngilizce",
    "videoURL": "https://example.com/video/inception.mp4"
  },

  {
    "isim": "The Godfather",
    "tür": "Suç",
    "çıkışYılı": 1972,
    "kapakURL": "https://example.com/kapak/godfather.jpg",
    "bannerURL": "https://example.com/banner/godfather.jpg",
    "açıklama": "İtalyan mafya ailesinin yükselişi ve çöküşü.",
    "puan": 9.2,
    "dil": "İngilizce",
    "videoURL": "https://example.com/video/godfather.mp4"
  },

  {
    "isim": "Interstellar",
    "tür": "Macera",
    "çıkışYılı": 2014,
    "kapakURL": "https://example.com/kapak/interstellar.jpg",
    "bannerURL": "https://example.com/banner/interstellar.jpg",
    "açıklama": "İnsanlık için yeni bir gezegen arayan bir ekibin yolculuğu.",
    "puan": 8.6,
    "dil": "İngilizce",
    "videoURL": "https://example.com/video/interstellar.mp4"
  },

  {
    "isim": "Spirited Away",
    "tür": "Animasyon",
    "çıkışYılı": 2001,
    "kapakURL": "https://example.com/kapak/spiritedaway.jpg",
    "bannerURL": "https://example.com/banner/spiritedaway.jpg",
    "açıklama": "Büyülü bir dünyada kaybolan bir kızın macerası.",
    "puan": 8.6,
    "dil": "Japonca",
    "videoURL": "https://example.com/video/spiritedaway.mp4"
  }
]
